pymoe/__init__.py
pymoe/anime/__init__.py
pymoe/anime/get/__init__.py
pymoe/anime/get/anilist.py
pymoe/anime/get/kitsu.py
pymoe/anime/get/mal.py
pymoe/anime/search/__init__.py
pymoe/anime/search/anilist.py
pymoe/anime/search/kitsu.py
pymoe/anime/search/mal.py
pymoe/ln/__init__.py
pymoe/ln/get/__init__.py
pymoe/ln/get/bakatsuki.py
pymoe/ln/get/wlnupdates.py
pymoe/ln/search/__init__.py
pymoe/ln/search/bakatsuki.py
pymoe/ln/search/wlnupdates.py
pymoe/manga/__init__.py
pymoe/manga/get/__init__.py
pymoe/manga/get/anilist.py
pymoe/manga/get/kitsu.py
pymoe/manga/get/mangaupdates.py
pymoe/manga/search/__init__.py
pymoe/manga/search/anilist.py
pymoe/manga/search/kitsu.py
pymoe/manga/search/mangaupdates.py
pymoe/utils/errors.py
pymoe/utils/helpers.py
pymoe-2.2.1.dist-info/LICENSE
pymoe-2.2.1.dist-info/METADATA
pymoe-2.2.1.dist-info/WHEEL
pymoe-2.2.1.dist-info/RECORD
