Metadata-Version: 2.1
Name: PyMoe
Version: 2.2.1
Summary: This is Pymoe. The only python library you'll need if you need information on Anime, Manga, Light Novels, or Visual Novels.
Author: Charles Click
Author-email: CharlesClick@vertinext.com
Requires-Python: >=3.10,<4.0
Classifier: Programming Language :: Python :: 3
Classifier: Programming Language :: Python :: 3.10
Classifier: Programming Language :: Python :: 3.11
Classifier: Programming Language :: Python :: 3.12
Requires-Dist: bs4
Requires-Dist: requests
Requires-Dist: ujson
